{
  "wordDatabase": [
    {
      "word": "BARN",
      "level": 1,
      "tags": [
        "Animals",
        "Farm",
        "Nature",
        "Food"
      ],
      "associations": [],
      "clue": "Farm storage",
      "clues": {
        "level3": "Farm storage",
        "level1": "A wild animal.",
        "level2": "An animal that can be a pet.",
        "level4": "An animal often seen in stories.",
        "level5": "A creature of lore."
      }
    },
    {
      "word": "BEE",
      "level": 1,
      "tags": [
        "Animals"
      ],
      "clue": "Honey maker",
      "associations": [],
      "clues": {
        "level3": "Honey maker",
        "level1": "A farm animal. A is for ___.",
        "level2": "A creature that lives outdoors.",
        "level4": "A wild creature often studied.",
        "level5": "A common creature in folklore."
      }
    },
    {
      "word": "CAT",
      "level": 1,
      "tags": [
        "Animals",
        "Farm",
        "Nature",
        "Food"
      ],
      "associations": [],
      "clue": "Purr-fect pet",
      "clues": {
        "level3": "Purr-fect pet",
        "level1": "A farm animal. A is for ___.",
        "level2": "A creature that lives outdoors.",
        "level4": "A wild creature often studied.",
        "level5": "A common creature in folklore."
      }
    },
    {
      "word": "COW",
      "level": 1,
      "tags": [
        "Animals",
        "Farm",
        "Nature",
        "Food"
      ],
      "associations": [],
      "clue": "Mooing milk giver",
      "clues": {
        "level3": "Mooing milk giver",
        "level1": "A wild animal.",
        "level2": "An animal that can be a pet.",
        "level4": "An animal often seen in stories.",
        "level5": "A creature of lore."
      }
    },
    {
      "word": "EGG",
      "level": 1,
      "tags": [
        "Animals",
        "Farm",
        "Nature",
        "Food",
        "Dinosaurs",
        "History",
        "Science",
        "Home",
        "Kitchen",
        "Health"
      ],
      "associations": [],
      "clue": "Breakfast staple",
      "clues": {
        "level3": "Breakfast staple",
        "level1": "A wild animal.",
        "level2": "An animal that can be a pet.",
        "level4": "An animal often seen in stories.",
        "level5": "A creature of lore."
      }
    },
    {
      "word": "HAY",
      "level": 1,
      "tags": [
        "Animals",
        "Farm",
        "Nature",
        "Food"
      ],
      "associations": [],
      "clue": "Farm bedding",
      "clues": {
        "level3": "Farm bedding",
        "level1": "A farm animal. A is for ___.",
        "level2": "A creature that lives outdoors.",
        "level4": "A wild creature often studied.",
        "level5": "A common creature in folklore."
      }
    },
    {
      "word": "HEN",
      "level": 1,
      "tags": [
        "Animals",
        "Farm",
        "Nature",
        "Food"
      ],
      "associations": [],
      "clue": "Egg-laying bird",
      "clues": {
        "level3": "Egg-laying bird",
        "level1": "A wild animal.",
        "level2": "An animal that can be a pet.",
        "level4": "An animal often seen in stories.",
        "level5": "A creature of lore."
      }
    },
    {
      "word": "OWL",
      "level": 1,
      "tags": [
        "Animals"
      ],
      "clue": "Wise night bird",
      "associations": [],
      "clues": {
        "level3": "Wise night bird",
        "level1": "A farm animal. A is for ___.",
        "level2": "A creature that lives outdoors.",
        "level4": "A wild creature often studied.",
        "level5": "A common creature in folklore."
      }
    },
    {
      "word": "PIG",
      "level": 1,
      "tags": [
        "Animals",
        "Farm",
        "Nature",
        "Food"
      ],
      "associations": [],
      "clue": "Oinky farm animal",
      "clues": {
        "level3": "Oinky farm animal",
        "level1": "A farm animal. A is for ___.",
        "level2": "A creature that lives outdoors.",
        "level4": "A wild creature often studied.",
        "level5": "A common creature in folklore."
      }
    },
    {
      "word": "RABBIT",
      "level": 1,
      "tags": [
        "Animals"
      ],
      "clue": "Hoppy hopper",
      "clues": {
        "level3": "Hoppy hopper",
        "level1": "A farm animal. A is for ___.",
        "level2": "A creature that lives outdoors.",
        "level4": "A wild creature often studied.",
        "level5": "A common creature in folklore."
      }
    },
    {
      "word": "BEAR",
      "level": 2,
      "tags": [
        "Animals"
      ],
      "clue": "Hibernating mammal",
      "clues": {
        "level3": "Hibernating mammal",
        "level1": "A farm animal. A is for ___.",
        "level2": "A creature that lives outdoors.",
        "level4": "A wild creature often studied.",
        "level5": "A common creature in folklore."
      }
    },
    {
      "word": "BUTTERFLY",
      "level": 2,
      "tags": [
        "Animals"
      ],
      "clue": "Colorful flyer",
      "associations": [],
      "clues": {
        "level3": "Colorful flyer",
        "level1": "A wild animal.",
        "level2": "An animal that can be a pet.",
        "level4": "An animal often seen in stories.",
        "level5": "A creature of lore."
      }
    },
    {
      "word": "CORN",
      "level": 2,
      "tags": [
        "Animals",
        "Farm",
        "Nature",
        "Food"
      ],
      "associations": [],
      "clue": "Yellow cob",
      "clues": {
        "level3": "Yellow cob",
        "level1": "A farm animal. A is for ___.",
        "level2": "A creature that lives outdoors.",
        "level4": "A wild creature often studied.",
        "level5": "A common creature in folklore."
      }
    },
    {
      "word": "DINOSAUR",
      "level": 2,
      "tags": [
        "Animals"
      ],
      "clue": "Extinct creature",
      "associations": [],
      "clues": {
        "level3": "Extinct creature",
        "level1": "A wild animal.",
        "level2": "An animal that can be a pet.",
        "level4": "An animal often seen in stories.",
        "level5": "A creature of lore."
      }
    },
    {
      "word": "DUCK",
      "level": 2,
      "tags": [
        "Animals",
        "Farm",
        "Nature",
        "Food"
      ],
      "associations": [],
      "clue": "Quacking swimmer",
      "clues": {
        "level3": "Quacking swimmer",
        "level1": "A wild animal.",
        "level2": "An animal that can be a pet.",
        "level4": "An animal often seen in stories.",
        "level5": "A creature of lore."
      }
    },
    {
      "word": "FIELD",
      "level": 2,
      "tags": [
        "Animals",
        "Farm",
        "Nature",
        "Food"
      ],
      "associations": [],
      "clue": "Open farmland",
      "clues": {
        "level3": "Open farmland",
        "level1": "A farm animal. A is for ___.",
        "level2": "A creature that lives outdoors.",
        "level4": "A wild creature often studied.",
        "level5": "A common creature in folklore."
      }
    },
    {
      "word": "FOX",
      "level": 2,
      "tags": [
        "Animals"
      ],
      "clue": "Cunning red predator",
      "clues": {
        "level3": "Cunning red predator",
        "level1": "A wild animal.",
        "level2": "An animal that can be a pet.",
        "level4": "An animal often seen in stories.",
        "level5": "A creature of lore."
      }
    },
    {
      "word": "GOAT",
      "level": 2,
      "tags": [
        "Animals",
        "Farm",
        "Nature",
        "Food"
      ],
      "associations": [],
      "clue": "Bearded climber",
      "clues": {
        "level3": "Bearded climber",
        "level1": "A wild animal.",
        "level2": "An animal that can be a pet.",
        "level4": "An animal often seen in stories.",
        "level5": "A creature of lore."
      }
    },
    {
      "word": "HORSE",
      "level": 2,
      "tags": [
        "Animals",
        "Farm",
        "Nature",
        "Food"
      ],
      "associations": [],
      "clue": "Galloping steed",
      "clues": {
        "level3": "Galloping steed",
        "level1": "A wild animal.",
        "level2": "An animal that can be a pet.",
        "level4": "An animal often seen in stories.",
        "level5": "A creature of lore."
      }
    },
    {
      "word": "MILK",
      "level": 2,
      "tags": [
        "Animals",
        "Farm",
        "Nature",
        "Food"
      ],
      "associations": [],
      "clue": "White drink",
      "clues": {
        "level3": "White drink",
        "level1": "A wild animal.",
        "level2": "An animal that can be a pet.",
        "level4": "An animal often seen in stories.",
        "level5": "A creature of lore."
      }
    },
    {
      "word": "PENGUIN",
      "level": 2,
      "tags": [
        "Animals"
      ],
      "clue": "Tuxedoed bird",
      "associations": [],
      "clues": {
        "level3": "Tuxedoed bird",
        "level1": "A farm animal. A is for ___.",
        "level2": "A creature that lives outdoors.",
        "level4": "A wild creature often studied.",
        "level5": "A common creature in folklore."
      }
    },
    {
      "word": "SHEEP",
      "level": 2,
      "tags": [
        "Animals",
        "Farm",
        "Nature",
        "Food"
      ],
      "associations": [],
      "clue": "Woolly grazer",
      "clues": {
        "level3": "Woolly grazer",
        "level1": "A wild animal.",
        "level2": "An animal that can be a pet.",
        "level4": "An animal often seen in stories.",
        "level5": "A creature of lore."
      }
    },
    {
      "word": "HARVEST",
      "level": 3,
      "tags": [
        "Animals",
        "Farm",
        "Nature",
        "Food"
      ],
      "associations": [],
      "clue": "Crop gathering",
      "clues": {
        "level3": "Crop gathering",
        "level1": "A wild animal.",
        "level2": "An animal that can be a pet.",
        "level4": "An animal often seen in stories.",
        "level5": "A creature of lore."
      }
    },
    {
      "word": "ORCHARD",
      "level": 3,
      "tags": [
        "Animals",
        "Farm",
        "Nature",
        "Food"
      ],
      "associations": [],
      "clue": "Fruit tree area",
      "clues": {
        "level3": "Fruit tree area",
        "level1": "A wild animal.",
        "level2": "An animal that can be a pet.",
        "level4": "An animal often seen in stories.",
        "level5": "A creature of lore."
      }
    },
    {
      "word": "PASTURE",
      "level": 3,
      "tags": [
        "Animals",
        "Farm",
        "Nature",
        "Food"
      ],
      "associations": [],
      "clue": "Animal grazing land",
      "clues": {
        "level3": "Animal grazing land",
        "level1": "A farm animal. A is for ___.",
        "level2": "A creature that lives outdoors.",
        "level4": "A wild creature often studied.",
        "level5": "A common creature in folklore."
      }
    },
    {
      "word": "ROOSTER",
      "level": 3,
      "tags": [
        "Animals",
        "Farm",
        "Nature",
        "Food"
      ],
      "associations": [],
      "clue": "Cock-a-doodle-doo bird",
      "clues": {
        "level3": "Cock-a-doodle-doo bird",
        "level1": "A farm animal. A is for ___.",
        "level2": "A creature that lives outdoors.",
        "level4": "A wild creature often studied.",
        "level5": "A common creature in folklore."
      }
    },
    {
      "word": "TRACTOR",
      "level": 3,
      "tags": [
        "Animals",
        "Farm",
        "Nature",
        "Food"
      ],
      "associations": [],
      "clue": "Farm machine",
      "clues": {
        "level3": "Farm machine",
        "level1": "A wild animal.",
        "level2": "An animal that can be a pet.",
        "level4": "An animal often seen in stories.",
        "level5": "A creature of lore."
      }
    },
    {
      "word": "ARM",
      "level": 1,
      "tags": [
        "Body",
        "Health",
        "Science",
        "Me"
      ],
      "associations": [],
      "clue": "Word from Body",
      "clues": {
        "level1": "A 3-letter word about body",
        "level2": "A 3-letter body answer",
        "level3": "Related to body",
        "level4": "Something linked to body",
        "level5": "Topic: Body"
      }
    },
    {
      "word": "EAR",
      "level": 1,
      "tags": [
        "Body",
        "Health",
        "Science",
        "Me"
      ],
      "associations": [],
      "clue": "Word from Body",
      "clues": {
        "level1": "Related to body",
        "level2": "Something linked to body",
        "level3": "Topic: Body",
        "level4": "A 3-letter word about body",
        "level5": "A 3-letter body answer"
      }
    },
    {
      "word": "EYE",
      "level": 1,
      "tags": [
        "Body",
        "Health",
        "Science",
        "Me"
      ],
      "associations": [],
      "clue": "Word from Body",
      "clues": {
        "level1": "Something linked to body",
        "level2": "Topic: Body",
        "level3": "A 3-letter word about body",
        "level4": "A 3-letter body answer",
        "level5": "Related to body"
      }
    },
    {
      "word": "LEG",
      "level": 1,
      "tags": [
        "Body",
        "Health",
        "Science",
        "Me"
      ],
      "associations": [],
      "clue": "Word from Body",
      "clues": {
        "level1": "Related to body",
        "level2": "Something linked to body",
        "level3": "Topic: Body",
        "level4": "A 3-letter word about body",
        "level5": "A 3-letter body answer"
      }
    },
    {
      "word": "TOE",
      "level": 1,
      "tags": [
        "Body",
        "Health",
        "Science",
        "Me"
      ],
      "associations": [],
      "clue": "Word from Body",
      "clues": {
        "level1": "Something linked to body",
        "level2": "Topic: Body",
        "level3": "A 3-letter word about body",
        "level4": "A 3-letter body answer",
        "level5": "Related to body"
      }
    },
    {
      "word": "FOOT",
      "level": 2,
      "tags": [
        "Body",
        "Health",
        "Science",
        "Me"
      ],
      "associations": [],
      "clue": "Word from Body",
      "clues": {
        "level1": "Something linked to body",
        "level2": "Topic: Body",
        "level3": "A 4-letter word about body",
        "level4": "A 4-letter body answer",
        "level5": "Related to body"
      }
    },
    {
      "word": "HAIR",
      "level": 2,
      "tags": [
        "Body",
        "Health",
        "Science",
        "Me"
      ],
      "associations": [],
      "clue": "Word from Body",
      "clues": {
        "level1": "Something linked to body",
        "level2": "Topic: Body",
        "level3": "A 4-letter word about body",
        "level4": "A 4-letter body answer",
        "level5": "Related to body"
      }
    },
    {
      "word": "HAND",
      "level": 2,
      "tags": [
        "Body",
        "Health",
        "Science",
        "Me"
      ],
      "associations": [],
      "clue": "Word from Body",
      "clues": {
        "level1": "Topic: Body",
        "level2": "A 4-letter word about body",
        "level3": "A 4-letter body answer",
        "level4": "Related to body",
        "level5": "Something linked to body"
      }
    },
    {
      "word": "HEAD",
      "level": 2,
      "tags": [
        "Body",
        "Health",
        "Science",
        "Me"
      ],
      "associations": [],
      "clue": "Word from Body",
      "clues": {
        "level1": "A 4-letter word about body",
        "level2": "A 4-letter body answer",
        "level3": "Related to body",
        "level4": "Something linked to body",
        "level5": "Topic: Body"
      }
    },
    {
      "word": "NOSE",
      "level": 2,
      "tags": [
        "Body",
        "Health",
        "Science",
        "Me"
      ],
      "associations": [],
      "clue": "Word from Body",
      "clues": {
        "level1": "A 4-letter word about body",
        "level2": "A 4-letter body answer",
        "level3": "Related to body",
        "level4": "Something linked to body",
        "level5": "Topic: Body"
      }
    },
    {
      "word": "SKIN",
      "level": 2,
      "tags": [
        "Body",
        "Health",
        "Science",
        "Me"
      ],
      "associations": [],
      "clue": "Word from Body",
      "clues": {
        "level1": "A 4-letter word about body",
        "level2": "A 4-letter body answer",
        "level3": "Related to body",
        "level4": "Something linked to body",
        "level5": "Topic: Body"
      }
    },
    {
      "word": "BRAIN",
      "level": 3,
      "tags": [
        "Body",
        "Health",
        "Science",
        "Me"
      ],
      "associations": [],
      "clue": "Word from Body",
      "clues": {
        "level1": "A 5-letter word about body",
        "level2": "A 5-letter body answer",
        "level3": "Related to body",
        "level4": "Something linked to body",
        "level5": "Topic: Body"
      }
    },
    {
      "word": "ELBOW",
      "level": 3,
      "tags": [
        "Body",
        "Health",
        "Science",
        "Me"
      ],
      "associations": [],
      "clue": "Word from Body",
      "clues": {
        "level1": "Something linked to body",
        "level2": "Topic: Body",
        "level3": "A 5-letter word about body",
        "level4": "A 5-letter body answer",
        "level5": "Related to body"
      }
    },
    {
      "word": "HEART",
      "level": 3,
      "tags": [
        "Body",
        "Health",
        "Science",
        "Me"
      ],
      "associations": [],
      "clue": "Word from Body",
      "clues": {
        "level1": "Something linked to body",
        "level2": "Topic: Body",
        "level3": "A 5-letter word about body",
        "level4": "A 5-letter body answer",
        "level5": "Related to body"
      }
    },
    {
      "word": "MUSCLE",
      "level": 3,
      "tags": [
        "Body",
        "Health",
        "Science",
        "Me"
      ],
      "associations": [],
      "clue": "Word from Body",
      "clues": {
        "level1": "Something linked to body",
        "level2": "Topic: Body",
        "level3": "A 6-letter word about body",
        "level4": "A 6-letter body answer",
        "level5": "Related to body"
      }
    },
    {
      "word": "SKELETON",
      "level": 3,
      "tags": [
        "Body",
        "Health",
        "Science",
        "Me"
      ],
      "associations": [],
      "clue": "Word from Body",
      "clues": {
        "level1": "Topic: Body",
        "level2": "A 8-letter word about body",
        "level3": "A 8-letter body answer",
        "level4": "Related to body",
        "level5": "Something linked to body"
      }
    },
    {
      "word": "STOMACH",
      "level": 3,
      "tags": [
        "Body",
        "Health",
        "Science",
        "Me"
      ],
      "associations": [],
      "clue": "Word from Body",
      "clues": {
        "level1": "Something linked to body",
        "level2": "Topic: Body",
        "level3": "A 7-letter word about body",
        "level4": "A 7-letter body answer",
        "level5": "Related to body"
      }
    },
    {
      "word": "BIG",
      "level": 1,
      "tags": [
        "Dinosaurs",
        "History",
        "Animals",
        "Science"
      ],
      "associations": [],
      "clue": "Word from Dinosaurs",
      "clues": {
        "level1": "A 3-letter dinosaurs answer",
        "level2": "Related to dinosaurs",
        "level3": "Something linked to dinosaurs",
        "level4": "Topic: Dinosaurs",
        "level5": "A 3-letter word about dinosaurs"
      }
    },
    {
      "word": "BONE",
      "level": 1,
      "tags": [
        "Dinosaurs",
        "History",
        "Animals",
        "Science"
      ],
      "associations": [],
      "clue": "Word from Dinosaurs",
      "clues": {
        "level1": "Something linked to dinosaurs",
        "level2": "Topic: Dinosaurs",
        "level3": "A 4-letter word about dinosaurs",
        "level4": "A 4-letter dinosaurs answer",
        "level5": "Related to dinosaurs"
      }
    },
    {
      "word": "REX",
      "level": 1,
      "tags": [
        "Dinosaurs",
        "History",
        "Animals",
        "Science"
      ],
      "associations": [],
      "clue": "Word from Dinosaurs",
      "clues": {
        "level1": "A 3-letter word about dinosaurs",
        "level2": "A 3-letter dinosaurs answer",
        "level3": "Related to dinosaurs",
        "level4": "Something linked to dinosaurs",
        "level5": "Topic: Dinosaurs"
      }
    },
    {
      "word": "CLAW",
      "level": 2,
      "tags": [
        "Dinosaurs",
        "History",
        "Animals",
        "Science"
      ],
      "associations": [],
      "clue": "Word from Dinosaurs",
      "clues": {
        "level1": "A 4-letter dinosaurs answer",
        "level2": "Related to dinosaurs",
        "level3": "Something linked to dinosaurs",
        "level4": "Topic: Dinosaurs",
        "level5": "A 4-letter word about dinosaurs"
      }
    },
    {
      "word": "FOSSIL",
      "level": 2,
      "tags": [
        "Dinosaurs",
        "History",
        "Animals",
        "Science"
      ],
      "associations": [],
      "clue": "Word from Dinosaurs",
      "clues": {
        "level1": "A 6-letter word about dinosaurs",
        "level2": "A 6-letter dinosaurs answer",
        "level3": "Related to dinosaurs",
        "level4": "Something linked to dinosaurs",
        "level5": "Topic: Dinosaurs"
      }
    },
    {
      "word": "ROAR",
      "level": 2,
      "tags": [
        "Dinosaurs",
        "History",
        "Animals",
        "Science"
      ],
      "associations": [],
      "clue": "Word from Dinosaurs",
      "clues": {
        "level1": "Topic: Dinosaurs",
        "level2": "A 4-letter word about dinosaurs",
        "level3": "A 4-letter dinosaurs answer",
        "level4": "Related to dinosaurs",
        "level5": "Something linked to dinosaurs"
      }
    },
    {
      "word": "SPIKE",
      "level": 2,
      "tags": [
        "Dinosaurs",
        "History",
        "Animals",
        "Science"
      ],
      "associations": [],
      "clue": "Word from Dinosaurs",
      "clues": {
        "level1": "A 5-letter dinosaurs answer",
        "level2": "Related to dinosaurs",
        "level3": "Something linked to dinosaurs",
        "level4": "Topic: Dinosaurs",
        "level5": "A 5-letter word about dinosaurs"
      }
    },
    {
      "word": "TEETH",
      "level": 2,
      "tags": [
        "Dinosaurs",
        "History",
        "Animals",
        "Science"
      ],
      "associations": [],
      "clue": "Word from Dinosaurs",
      "clues": {
        "level1": "Topic: Dinosaurs",
        "level2": "A 5-letter word about dinosaurs",
        "level3": "A 5-letter dinosaurs answer",
        "level4": "Related to dinosaurs",
        "level5": "Something linked to dinosaurs"
      }
    },
    {
      "word": "TLEAF",
      "level": 2,
      "tags": [
        "Dinosaurs",
        "History",
        "Animals",
        "Science"
      ],
      "associations": [],
      "clue": "Word from Dinosaurs",
      "clues": {
        "level1": "A 5-letter word about dinosaurs",
        "level2": "A 5-letter dinosaurs answer",
        "level3": "Related to dinosaurs",
        "level4": "Something linked to dinosaurs",
        "level5": "Topic: Dinosaurs"
      }
    },
    {
      "word": "EXTINCT",
      "level": 3,
      "tags": [
        "Dinosaurs",
        "History",
        "Animals",
        "Science"
      ],
      "associations": [],
      "clue": "Word from Dinosaurs",
      "clues": {
        "level1": "Topic: Dinosaurs",
        "level2": "A 7-letter word about dinosaurs",
        "level3": "A 7-letter dinosaurs answer",
        "level4": "Related to dinosaurs",
        "level5": "Something linked to dinosaurs"
      }
    },
    {
      "word": "JURASSIC",
      "level": 3,
      "tags": [
        "Dinosaurs",
        "History",
        "Animals",
        "Science"
      ],
      "associations": [],
      "clue": "Word from Dinosaurs",
      "clues": {
        "level1": "Something linked to dinosaurs",
        "level2": "Topic: Dinosaurs",
        "level3": "A 8-letter word about dinosaurs",
        "level4": "A 8-letter dinosaurs answer",
        "level5": "Related to dinosaurs"
      }
    },
    {
      "word": "RAPTOR",
      "level": 3,
      "tags": [
        "Dinosaurs",
        "History",
        "Animals",
        "Science"
      ],
      "associations": [],
      "clue": "Word from Dinosaurs",
      "clues": {
        "level1": "Something linked to dinosaurs",
        "level2": "Topic: Dinosaurs",
        "level3": "A 6-letter word about dinosaurs",
        "level4": "A 6-letter dinosaurs answer",
        "level5": "Related to dinosaurs"
      }
    },
    {
      "word": "REPTILE",
      "level": 3,
      "tags": [
        "Dinosaurs",
        "History",
        "Animals",
        "Science"
      ],
      "associations": [],
      "clue": "Word from Dinosaurs",
      "clues": {
        "level1": "Topic: Dinosaurs",
        "level2": "A 7-letter word about dinosaurs",
        "level3": "A 7-letter dinosaurs answer",
        "level4": "Related to dinosaurs",
        "level5": "Something linked to dinosaurs"
      }
    },
    {
      "word": "TRICERATOPS",
      "level": 3,
      "tags": [
        "Dinosaurs",
        "History",
        "Animals",
        "Science"
      ],
      "associations": [],
      "clue": "Word from Dinosaurs",
      "clues": {
        "level1": "Topic: Dinosaurs",
        "level2": "Some 11-letter word about dinosaurs",
        "level3": "Some 11-letter dinosaurs answer",
        "level4": "Related to dinosaurs",
        "level5": "Something linked to dinosaurs"
      }
    },
    {
      "word": "VOLCANO",
      "level": 3,
      "tags": [
        "Dinosaurs",
        "History",
        "Animals",
        "Science"
      ],
      "associations": [],
      "clue": "Word from Dinosaurs",
      "clues": {
        "level1": "A 7-letter dinosaurs answer",
        "level2": "Related to dinosaurs",
        "level3": "Something linked to dinosaurs",
        "level4": "Topic: Dinosaurs",
        "level5": "A 7-letter word about dinosaurs"
      }
    },
    {
      "word": "ELF",
      "level": 1,
      "tags": [
        "Fantasy",
        "Stories",
        "Magic",
        "Books"
      ],
      "associations": [],
      "clue": "Word from Fantasy",
      "clues": {
        "level1": "A magical creature.",
        "level2": "Something from a fairy tale.",
        "level3": "A mythical creature.",
        "level4": "A myth or legend item.",
        "level5": "A creature of lore."
      }
    },
    {
      "word": "FROG",
      "level": 1,
      "tags": [
        "Fantasy",
        "Stories",
        "Magic",
        "Books"
      ],
      "associations": [],
      "clue": "Word from Fantasy",
      "clues": {
        "level1": "A magic word.",
        "level2": "A creature from a fantasy tale.",
        "level3": "A fantasy story word.",
        "level4": "A legend creature.",
        "level5": "A mystical or arcane word."
      }
    },
    {
      "word": "HERO",
      "level": 1,
      "tags": [
        "Fantasy",
        "Stories",
        "Magic",
        "Books"
      ],
      "associations": [],
      "clue": "Word from Fantasy",
      "clues": {
        "level1": "A magic word.",
        "level2": "A creature from a fantasy tale.",
        "level3": "A fantasy story word.",
        "level4": "A legend creature.",
        "level5": "A mystical or arcane word."
      }
    },
    {
      "word": "KING",
      "level": 1,
      "tags": [
        "Fantasy",
        "Stories",
        "Magic",
        "Books"
      ],
      "associations": [],
      "clue": "Word from Fantasy",
      "clues": {
        "level1": "A magical creature.",
        "level2": "Something from a fairy tale.",
        "level3": "A mythical creature.",
        "level4": "A myth or legend item.",
        "level5": "A creature of lore."
      }
    },
    {
      "word": "WAND",
      "level": 1,
      "tags": [
        "Fantasy",
        "Stories",
        "Magic",
        "Books"
      ],
      "associations": [],
      "clue": "Word from Fantasy",
      "clues": {
        "level1": "A magic word.",
        "level2": "A creature from a fantasy tale.",
        "level3": "A fantasy story word.",
        "level4": "A legend creature.",
        "level5": "A mystical or arcane word."
      }
    },
    {
      "word": "BOOK",
      "level": 2,
      "tags": [
        "Fantasy",
        "Stories",
        "Magic",
        "Books"
      ],
      "associations": [],
      "clue": "Word from Fantasy",
      "clues": {
        "level1": "A magical creature.",
        "level2": "Something from a fairy tale.",
        "level3": "A mythical creature.",
        "level4": "A myth or legend item.",
        "level5": "A creature of lore."
      }
    },
    {
      "word": "FAIRY",
      "level": 2,
      "tags": [
        "Fantasy",
        "Stories",
        "Magic",
        "Books"
      ],
      "associations": [],
      "clue": "Word from Fantasy",
      "clues": {
        "level1": "A magical creature.",
        "level2": "Something from a fairy tale.",
        "level3": "A mythical creature.",
        "level4": "A myth or legend item.",
        "level5": "A creature of lore."
      }
    },
    {
      "word": "GIANT",
      "level": 2,
      "tags": [
        "Fantasy",
        "Stories",
        "Magic",
        "Books"
      ],
      "associations": [],
      "clue": "Word from Fantasy",
      "clues": {
        "level1": "A magical creature.",
        "level2": "Something from a fairy tale.",
        "level3": "A mythical creature.",
        "level4": "A myth or legend item.",
        "level5": "A creature of lore."
      }
    },
    {
      "word": "MAGIC",
      "level": 2,
      "tags": [
        "Fantasy",
        "Stories",
        "Magic",
        "Books"
      ],
      "associations": [],
      "clue": "Word from Fantasy",
      "clues": {
        "level1": "A magical creature.",
        "level2": "Something from a fairy tale.",
        "level3": "A mythical creature.",
        "level4": "A myth or legend item.",
        "level5": "A creature of lore."
      }
    },
    {
      "word": "QUEEN",
      "level": 2,
      "tags": [
        "Fantasy",
        "Stories",
        "Magic",
        "Books"
      ],
      "associations": [],
      "clue": "Word from Fantasy",
      "clues": {
        "level1": "A magic word.",
        "level2": "A creature from a fantasy tale.",
        "level3": "A fantasy story word.",
        "level4": "A legend creature.",
        "level5": "A mystical or arcane word."
      }
    },
    {
      "word": "WITCH",
      "level": 2,
      "tags": [
        "Fantasy",
        "Stories",
        "Magic",
        "Books"
      ],
      "associations": [],
      "clue": "Word from Fantasy",
      "clues": {
        "level1": "A magical creature.",
        "level2": "Something from a fairy tale.",
        "level3": "A mythical creature.",
        "level4": "A myth or legend item.",
        "level5": "A creature of lore."
      }
    },
    {
      "word": "CASTLE",
      "level": 3,
      "tags": [
        "Fantasy",
        "Stories",
        "Magic",
        "Books"
      ],
      "associations": [],
      "clue": "Word from Fantasy",
      "clues": {
        "level1": "A magic word.",
        "level2": "A creature from a fantasy tale.",
        "level3": "A fantasy story word.",
        "level4": "A legend creature.",
        "level5": "A mystical or arcane word."
      }
    },
    {
      "word": "DRAGON",
      "level": 3,
      "tags": [
        "Fantasy",
        "Stories",
        "Magic",
        "Books"
      ],
      "associations": [],
      "clue": "Word from Fantasy",
      "clues": {
        "level1": "A magical creature.",
        "level2": "Something from a fairy tale.",
        "level3": "A mythical creature.",
        "level4": "A myth or legend item.",
        "level5": "A creature of lore."
      }
    },
    {
      "word": "KNIGHT",
      "level": 3,
      "tags": [
        "Fantasy",
        "Stories",
        "Magic",
        "Books"
      ],
      "associations": [],
      "clue": "Word from Fantasy",
      "clues": {
        "level1": "A magical creature.",
        "level2": "Something from a fairy tale.",
        "level3": "A mythical creature.",
        "level4": "A myth or legend item.",
        "level5": "A creature of lore."
      }
    },
    {
      "word": "MERMAID",
      "level": 3,
      "tags": [
        "Fantasy",
        "Stories",
        "Magic",
        "Books"
      ],
      "associations": [],
      "clue": "Word from Fantasy",
      "clues": {
        "level1": "A magical creature.",
        "level2": "Something from a fairy tale.",
        "level3": "A mythical creature.",
        "level4": "A myth or legend item.",
        "level5": "A creature of lore."
      }
    },
    {
      "word": "PRINCESS",
      "level": 3,
      "tags": [
        "Fantasy",
        "Stories",
        "Magic",
        "Books"
      ],
      "associations": [],
      "clue": "Word from Fantasy",
      "clues": {
        "level1": "A magical creature.",
        "level2": "Something from a fairy tale.",
        "level3": "A mythical creature.",
        "level4": "A myth or legend item.",
        "level5": "A creature of lore."
      }
    },
    {
      "word": "UNICORN",
      "level": 3,
      "tags": [
        "Fantasy",
        "Stories",
        "Magic",
        "Books"
      ],
      "associations": [],
      "clue": "Word from Fantasy",
      "clues": {
        "level1": "A magic word.",
        "level2": "A creature from a fantasy tale.",
        "level3": "A fantasy story word.",
        "level4": "A legend creature.",
        "level5": "A mystical or arcane word."
      }
    },
    {
      "word": "BUN",
      "level": 1,
      "tags": [
        "Food",
        "Home",
        "Kitchen",
        "Health"
      ],
      "associations": [],
      "clue": "Word from Food",
      "clues": {
        "level1": "A yummy food.",
        "level2": "A food you might have.",
        "level3": "A food word.",
        "level4": "A common meal item.",
        "level5": "A gastronomy word."
      }
    },
    {
      "word": "JAM",
      "level": 1,
      "tags": [
        "Food",
        "Home",
        "Kitchen",
        "Health"
      ],
      "associations": [],
      "clue": "Word from Food",
      "clues": {
        "level1": "Something you can eat.",
        "level2": "A kitchen item to eat.",
        "level3": "A type of food.",
        "level4": "A food term.",
        "level5": "A culinary word."
      }
    },
    {
      "word": "NUT",
      "level": 1,
      "tags": [
        "Food",
        "Home",
        "Kitchen",
        "Health"
      ],
      "associations": [],
      "clue": "Word from Food",
      "clues": {
        "level1": "A yummy food.",
        "level2": "A food you might have.",
        "level3": "A food word.",
        "level4": "A common meal item.",
        "level5": "A gastronomy word."
      }
    },
    {
      "word": "PIE",
      "level": 1,
      "tags": [
        "Food",
        "Home",
        "Kitchen",
        "Health"
      ],
      "associations": [],
      "clue": "Word from Food",
      "clues": {
        "level1": "Something you can eat.",
        "level2": "A kitchen item to eat.",
        "level3": "A type of food.",
        "level4": "A food term.",
        "level5": "A culinary word."
      }
    },
    {
      "word": "APPLE",
      "level": 2,
      "tags": [
        "Food",
        "Home",
        "Kitchen",
        "Health"
      ],
      "associations": [],
      "clue": "Crunchy fruit",
      "clues": {
        "level3": "Crunchy fruit",
        "level1": "Something you can eat.",
        "level2": "A kitchen item to eat.",
        "level4": "A food term.",
        "level5": "A culinary word."
      }
    },
    {
      "word": "BREAD",
      "level": 2,
      "tags": [
        "Food",
        "Home",
        "Kitchen",
        "Health"
      ],
      "associations": [],
      "clue": "Word from Food",
      "clues": {
        "level1": "Something you can eat.",
        "level2": "A kitchen item to eat.",
        "level3": "A type of food.",
        "level4": "A food term.",
        "level5": "A culinary word."
      }
    },
    {
      "word": "FRUIT",
      "level": 2,
      "tags": [
        "Food",
        "Home",
        "Kitchen",
        "Health"
      ],
      "associations": [],
      "clue": "Word from Food",
      "clues": {
        "level1": "Something you can eat.",
        "level2": "A kitchen item to eat.",
        "level3": "A type of food.",
        "level4": "A food term.",
        "level5": "A culinary word."
      }
    },
    {
      "word": "LUNCH",
      "level": 2,
      "tags": [
        "Food",
        "Home",
        "Kitchen",
        "Health"
      ],
      "associations": [],
      "clue": "Word from Food",
      "clues": {
        "level1": "Something you can eat.",
        "level2": "A kitchen item to eat.",
        "level3": "A type of food.",
        "level4": "A food term.",
        "level5": "A culinary word."
      }
    },
    {
      "word": "PIZZA",
      "level": 2,
      "tags": [
        "Food",
        "Home",
        "Kitchen",
        "Health"
      ],
      "associations": [],
      "clue": "Word from Food",
      "clues": {
        "level1": "Something you can eat.",
        "level2": "A kitchen item to eat.",
        "level3": "A type of food.",
        "level4": "A food term.",
        "level5": "A culinary word."
      }
    },
    {
      "word": "TACO",
      "level": 2,
      "tags": [
        "Food",
        "Home",
        "Kitchen",
        "Health"
      ],
      "associations": [],
      "clue": "Word from Food",
      "clues": {
        "level1": "A yummy food.",
        "level2": "A food you might have.",
        "level3": "A food word.",
        "level4": "A common meal item.",
        "level5": "A gastronomy word."
      }
    },
    {
      "word": "BAKERY",
      "level": 3,
      "tags": [
        "Food",
        "Home",
        "Kitchen",
        "Health"
      ],
      "associations": [],
      "clue": "Word from Food",
      "clues": {
        "level1": "Something you can eat.",
        "level2": "A kitchen item to eat.",
        "level3": "A type of food.",
        "level4": "A food term.",
        "level5": "A culinary word."
      }
    },
    {
      "word": "DESSERT",
      "level": 3,
      "tags": [
        "Food",
        "Home",
        "Kitchen",
        "Health"
      ],
      "associations": [],
      "clue": "Word from Food",
      "clues": {
        "level1": "Something you can eat.",
        "level2": "A kitchen item to eat.",
        "level3": "A type of food.",
        "level4": "A food term.",
        "level5": "A culinary word."
      }
    },
    {
      "word": "OMELET",
      "level": 3,
      "tags": [
        "Food",
        "Home",
        "Kitchen",
        "Health"
      ],
      "associations": [],
      "clue": "Word from Food",
      "clues": {
        "level1": "Something you can eat.",
        "level2": "A kitchen item to eat.",
        "level3": "A type of food.",
        "level4": "A food term.",
        "level5": "A culinary word."
      }
    },
    {
      "word": "RESTAURANT",
      "level": 3,
      "tags": [
        "Food",
        "Home",
        "Kitchen",
        "Health"
      ],
      "associations": [],
      "clue": "Word from Food",
      "clues": {
        "level1": "A yummy food.",
        "level2": "A food you might have.",
        "level3": "A food word.",
        "level4": "A common meal item.",
        "level5": "A gastronomy word."
      }
    },
    {
      "word": "SPAGHETTI",
      "level": 3,
      "tags": [
        "Food",
        "Home",
        "Kitchen",
        "Health"
      ],
      "associations": [],
      "clue": "Word from Food",
      "clues": {
        "level1": "A yummy food.",
        "level2": "A food you might have.",
        "level3": "A food word.",
        "level4": "A common meal item.",
        "level5": "A gastronomy word."
      }
    },
    {
      "word": "VEGETABLE",
      "level": 3,
      "tags": [
        "Food",
        "Home",
        "Kitchen",
        "Health"
      ],
      "associations": [],
      "clue": "Word from Food",
      "clues": {
        "level1": "A yummy food.",
        "level2": "A food you might have.",
        "level3": "A food word.",
        "level4": "A common meal item.",
        "level5": "A gastronomy word."
      }
    },
    {
      "word": "BLUEBERRY",
      "level": 2,
      "tags": [
        "Fruits"
      ],
      "clue": "Tiny blue fruit",
      "clues": {
        "level3": "Tiny blue fruit",
        "level1": "A 9-letter word about fruits",
        "level2": "A 9-letter fruits answer",
        "level4": "Something linked to fruits",
        "level5": "Topic: Fruits"
      }
    },
    {
      "word": "COCONUT",
      "level": 2,
      "tags": [
        "Fruits"
      ],
      "clue": "Hairy tropical nut",
      "associations": [],
      "clues": {
        "level3": "Hairy tropical nut",
        "level1": "A 7-letter word about fruits",
        "level2": "A 7-letter fruits answer",
        "level4": "Something linked to fruits",
        "level5": "Topic: Fruits"
      }
    },
    {
      "word": "PINEAPPLE",
      "level": 2,
      "tags": [
        "Fruits"
      ],
      "clue": "Spiky tropical fruit",
      "associations": [],
      "clues": {
        "level3": "Spiky tropical fruit",
        "level1": "A 9-letter fruits answer",
        "level2": "Related to fruits",
        "level4": "Topic: Fruits",
        "level5": "A 9-letter word about fruits"
      }
    },
    {
      "word": "STRAWBERRY",
      "level": 2,
      "tags": [
        "Fruits"
      ],
      "clue": "Red juicy berry",
      "clues": {
        "level3": "Red juicy berry",
        "level1": "A 10-letter word about fruits",
        "level2": "A 10-letter fruits answer",
        "level4": "Something linked to fruits",
        "level5": "Topic: Fruits"
      }
    },
    {
      "word": "TOMATO",
      "level": 2,
      "tags": [
        "Fruits"
      ],
      "clue": "Word from Fruits",
      "clues": {
        "level1": "Topic: Fruits",
        "level2": "A 6-letter word about fruits",
        "level3": "A 6-letter fruits answer",
        "level4": "Related to fruits",
        "level5": "Something linked to fruits"
      }
    },
    {
      "word": "WATERMELON",
      "level": 2,
      "tags": [
        "Fruits"
      ],
      "clue": "Summer melon",
      "associations": [],
      "clues": {
        "level3": "Summer melon",
        "level1": "Related to fruits",
        "level2": "Something linked to fruits",
        "level4": "A 10-letter word about fruits",
        "level5": "A 10-letter fruits answer"
      }
    },
    {
      "word": "CARDS",
      "level": 2,
      "tags": [
        "Games"
      ],
      "clue": "Playing deck",
      "associations": [],
      "clues": {
        "level3": "Playing deck",
        "level1": "Some 5-letter games answer",
        "level2": "Related to games",
        "level4": "Topic: Games",
        "level5": "Some 5-letter word about games"
      }
    },
    {
      "word": "DICE",
      "level": 2,
      "tags": [
        "Games"
      ],
      "clue": "Number cubes",
      "associations": [],
      "clues": {
        "level3": "Number cubes",
        "level1": "Something linked to games",
        "level2": "Topic: Games",
        "level4": "A 4-letter games answer",
        "level5": "Related to games"
      }
    },
    {
      "word": "PUZZLE",
      "level": 2,
      "tags": [
        "Games"
      ],
      "clue": "Brain teaser",
      "clues": {
        "level3": "Brain teaser",
        "level1": "A 6-letter games answer",
        "level2": "Related to games",
        "level4": "Topic: Games",
        "level5": "A 6-letter word about games"
      }
    },
    {
      "word": "CHESS",
      "level": 3,
      "tags": [
        "Games"
      ],
      "clue": "Strategic board game",
      "clues": {
        "level3": "Strategic board game",
        "level1": "A 5-letter word about games",
        "level2": "A 5-letter games answer",
        "level4": "Something linked to games",
        "level5": "Topic: Games"
      }
    },
    {
      "word": "CRAB",
      "level": 1,
      "tags": [
        "Ocean",
        "Animals",
        "Water",
        "Nature"
      ],
      "associations": [],
      "clue": "Sidewalking crustacean",
      "clues": {
        "level3": "Sidewalking crustacean",
        "level1": "Something from the sea.",
        "level2": "A thing found in the ocean.",
        "level4": "A sea-related term.",
        "level5": "A nautical word."
      }
    },
    {
      "word": "FISH",
      "level": 1,
      "tags": [
        "Ocean",
        "Animals",
        "Water",
        "Nature"
      ],
      "associations": [],
      "clue": "Finny swimmer",
      "clues": {
        "level3": "Finny swimmer",
        "level1": "Something from the sea.",
        "level2": "A thing found in the ocean.",
        "level4": "A sea-related term.",
        "level5": "A nautical word."
      }
    },
    {
      "word": "SAND",
      "level": 1,
      "tags": [
        "Ocean",
        "Animals",
        "Water",
        "Nature"
      ],
      "associations": [],
      "clue": "Beach grains",
      "clues": {
        "level3": "Beach grains",
        "level1": "Something from the sea.",
        "level2": "A thing found in the ocean.",
        "level4": "A sea-related term.",
        "level5": "A nautical word."
      }
    },
    {
      "word": "SEAL",
      "level": 1,
      "tags": [
        "Ocean",
        "Animals",
        "Water",
        "Nature"
      ],
      "associations": [],
      "clue": "Barking swimmer",
      "clues": {
        "level3": "Barking swimmer",
        "level1": "A sea creature or thing.",
        "level2": "A sea or ocean word.",
        "level4": "A marine term.",
        "level5": "An ocean term."
      }
    },
    {
      "word": "WET",
      "level": 1,
      "tags": [
        "Ocean",
        "Animals",
        "Water",
        "Nature"
      ],
      "associations": [],
      "clue": "Soaked condition",
      "clues": {
        "level3": "Soaked condition",
        "level1": "Something from the sea.",
        "level2": "A thing found in the ocean.",
        "level4": "A sea-related term.",
        "level5": "A nautical word."
      }
    },
    {
      "word": "BEACH",
      "level": 2,
      "tags": [
        "Ocean",
        "Animals",
        "Water",
        "Nature"
      ],
      "associations": [],
      "clue": "Sandy shore",
      "clues": {
        "level3": "Sandy shore",
        "level1": "A sea creature or thing.",
        "level2": "A sea or ocean word.",
        "level4": "A marine term.",
        "level5": "An ocean term."
      }
    },
    {
      "word": "CORAL",
      "level": 2,
      "tags": [
        "Ocean",
        "Animals",
        "Water",
        "Nature"
      ],
      "associations": [],
      "clue": "Undersea reef",
      "clues": {
        "level3": "Undersea reef",
        "level1": "A sea creature or thing.",
        "level2": "A sea or ocean word.",
        "level4": "A marine term.",
        "level5": "An ocean term."
      }
    },
    {
      "word": "LIGHTHOUSE",
      "level": 2,
      "tags": [
        "Ocean"
      ],
      "clue": "Guiding beacon",
      "associations": [],
      "clues": {
        "level3": "Guiding beacon",
        "level1": "Something from the sea.",
        "level2": "A thing found in the ocean.",
        "level4": "A sea-related term.",
        "level5": "A nautical word."
      }
    },
    {
      "word": "SCUBA",
      "level": 2,
      "tags": [
        "Ocean",
        "Animals",
        "Water",
        "Nature"
      ],
      "associations": [],
      "clue": "Underwater gear",
      "clues": {
        "level3": "Underwater gear",
        "level1": "Something from the sea.",
        "level2": "A thing found in the ocean.",
        "level4": "A sea-related term.",
        "level5": "A nautical word."
      }
    },
    {
      "word": "SHARK",
      "level": 2,
      "tags": [
        "Ocean",
        "Animals",
        "Water",
        "Nature"
      ],
      "associations": [],
      "clue": "Jagged-tooth predator",
      "clues": {
        "level3": "Jagged-tooth predator",
        "level1": "A sea creature or thing.",
        "level2": "A sea or ocean word.",
        "level4": "A marine term.",
        "level5": "An ocean term."
      }
    },
    {
      "word": "SHELL",
      "level": 2,
      "tags": [
        "Ocean",
        "Animals",
        "Water",
        "Nature"
      ],
      "associations": [],
      "clue": "Seashell home",
      "clues": {
        "level1": "Something from the sea.",
        "level2": "A thing found in the ocean.",
        "level3": "An ocean-related word.",
        "level4": "A sea-related term.",
        "level5": "A nautical word."
      }
    },
    {
      "word": "WHALE",
      "level": 2,
      "tags": [
        "Ocean",
        "Animals",
        "Water",
        "Nature"
      ],
      "associations": [],
      "clue": "Ocean giant",
      "clues": {
        "level3": "Ocean giant",
        "level1": "A sea creature or thing.",
        "level2": "A sea or ocean word.",
        "level4": "A marine term.",
        "level5": "An ocean term."
      }
    },
    {
      "word": "ATLANTIC",
      "level": 3,
      "tags": [
        "Ocean",
        "Animals",
        "Water",
        "Nature"
      ],
      "associations": [],
      "clue": "Word from Ocean",
      "clues": {
        "level1": "Something from the sea.",
        "level2": "A thing found in the ocean.",
        "level3": "An ocean-related word.",
        "level4": "A sea-related term.",
        "level5": "A nautical word."
      }
    },
    {
      "word": "DOLPHIN",
      "level": 3,
      "tags": [
        "Ocean",
        "Animals",
        "Water",
        "Nature"
      ],
      "associations": [],
      "clue": "Intelligent cetacean",
      "clues": {
        "level3": "Intelligent cetacean",
        "level1": "Something from the sea.",
        "level2": "A thing found in the ocean.",
        "level4": "A sea-related term.",
        "level5": "A nautical word."
      }
    },
    {
      "word": "LOBSTER",
      "level": 3,
      "tags": [
        "Ocean",
        "Animals",
        "Water",
        "Nature"
      ],
      "associations": [],
      "clue": "Word from Ocean",
      "clues": {
        "level1": "A sea creature or thing.",
        "level2": "A sea or ocean word.",
        "level3": "A marine word.",
        "level4": "A marine term.",
        "level5": "An ocean term."
      }
    },
    {
      "word": "OCTOPUS",
      "level": 3,
      "tags": [
        "Ocean",
        "Animals",
        "Water",
        "Nature"
      ],
      "associations": [],
      "clue": "Word from Ocean",
      "clues": {
        "level1": "Some sea creature or thing.",
        "level2": "Some sea or ocean word.",
        "level3": "Some marine word.",
        "level4": "Some marine term.",
        "level5": "some ocean term."
      }
    },
    {
      "word": "SEAHORSE",
      "level": 3,
      "tags": [
        "Ocean",
        "Animals",
        "Water",
        "Nature"
      ],
      "associations": [],
      "clue": "Word from Ocean",
      "clues": {
        "level1": "Something from the sea.",
        "level2": "A thing found in the ocean.",
        "level3": "An ocean-related word.",
        "level4": "A sea-related term.",
        "level5": "A nautical word."
      }
    },
    {
      "word": "TSUNAMI",
      "level": 3,
      "tags": [
        "Ocean",
        "Animals",
        "Water",
        "Nature"
      ],
      "associations": [],
      "clue": "Word from Ocean",
      "clues": {
        "level1": "A sea creature or thing.",
        "level2": "A sea or ocean word.",
        "level3": "A marine word.",
        "level4": "A marine term.",
        "level5": "An ocean term."
      }
    },
    {
      "word": "DESK",
      "level": 1,
      "tags": [
        "School"
      ],
      "clue": "Work surface",
      "associations": [],
      "clues": {
        "level3": "Work surface",
        "level1": "A 4-letter school answer",
        "level2": "Related to school",
        "level4": "Topic: School",
        "level5": "A 4-letter word about school"
      }
    },
    {
      "word": "GYM",
      "level": 1,
      "tags": [
        "School"
      ],
      "clue": "Exercise room",
      "clues": {
        "level3": "Exercise room",
        "level1": "Something linked to school",
        "level2": "Topic: School",
        "level4": "A 3-letter school answer",
        "level5": "Related to school"
      }
    },
    {
      "word": "ART",
      "level": 2,
      "tags": [
        "School"
      ],
      "clue": "Creative expression",
      "clues": {
        "level3": "Creative expression",
        "level1": "Related to school",
        "level2": "Something linked to school",
        "level4": "A 3-letter word about school",
        "level5": "A 3-letter school answer"
      }
    },
    {
      "word": "CAFETERIA",
      "level": 2,
      "tags": [
        "School"
      ],
      "clue": "Lunch room",
      "clues": {
        "level3": "Lunch room",
        "level1": "A 9-letter word about school",
        "level2": "A 9-letter school answer",
        "level4": "Something linked to school",
        "level5": "Topic: School"
      }
    },
    {
      "word": "COMPUTER",
      "level": 2,
      "tags": [
        "School"
      ],
      "clue": "Digital machine",
      "associations": [],
      "clues": {
        "level3": "Digital machine",
        "level1": "Topic: School",
        "level2": "A 8-letter word about school",
        "level4": "Related to school",
        "level5": "Something linked to school"
      }
    },
    {
      "word": "MUSIC",
      "level": 2,
      "tags": [
        "School"
      ],
      "clue": "Melodious sounds",
      "clues": {
        "level3": "Melodious sounds",
        "level1": "A 5-letter school answer",
        "level2": "Related to school",
        "level4": "Topic: School",
        "level5": "A 5-letter word about school"
      }
    },
    {
      "word": "PRINCIPAL",
      "level": 3,
      "tags": [
        "School"
      ],
      "clue": "School leader",
      "clues": {
        "level3": "School leader",
        "level1": "A 9-letter word about school",
        "level2": "A 9-letter school answer",
        "level4": "Something linked to school",
        "level5": "Topic: School"
      }
    },
    {
      "word": "MOON",
      "level": 1,
      "tags": [
        "Space",
        "Science",
        "Sky",
        "Travel"
      ],
      "associations": [],
      "clue": "Night sky orb",
      "clues": {
        "level3": "Night sky orb",
        "level1": "A starry-sky thing.",
        "level2": "Something seen in the night sky.",
        "level4": "A solar system term.",
        "level5": "A cosmic term."
      }
    },
    {
      "word": "SKY",
      "level": 1,
      "tags": [
        "Space",
        "Science",
        "Sky",
        "Travel"
      ],
      "associations": [],
      "clue": "Blue overhead",
      "clues": {
        "level3": "Blue overhead",
        "level1": "A starry-sky thing.",
        "level2": "Something seen in the night sky.",
        "level4": "A solar system term.",
        "level5": "A cosmic term."
      }
    },
    {
      "word": "STAR",
      "level": 1,
      "tags": [
        "Space",
        "Science",
        "Sky",
        "Travel"
      ],
      "associations": [],
      "clue": "Twinkling light",
      "clues": {
        "level3": "Twinkling light",
        "level1": "Something in space.",
        "level2": "A night-sky object.",
        "level4": "An astronomy word.",
        "level5": "A celestial object."
      }
    },
    {
      "word": "SUN",
      "level": 1,
      "tags": [
        "Space",
        "Science",
        "Sky",
        "Travel",
        "Weather",
        "Nature"
      ],
      "associations": [],
      "clue": "Daytime star",
      "clues": {
        "level3": "Daytime star",
        "level1": "Something in space.",
        "level2": "A night-sky object.",
        "level4": "An astronomy word.",
        "level5": "A celestial object."
      }
    },
    {
      "word": "UFO",
      "level": 1,
      "tags": [
        "Space",
        "Science",
        "Sky",
        "Travel"
      ],
      "associations": [],
      "clue": "Flying saucer",
      "clues": {
        "level3": "Flying saucer",
        "level1": "Something in space.",
        "level2": "A night-sky object.",
        "level4": "An astronomy word.",
        "level5": "A celestial object."
      }
    },
    {
      "word": "ALIEN",
      "level": 2,
      "tags": [
        "Space",
        "Science",
        "Sky",
        "Travel"
      ],
      "associations": [],
      "clue": "Space visitor",
      "clues": {
        "level3": "Space visitor",
        "level1": "A starry-sky thing.",
        "level2": "Something seen in the night sky.",
        "level4": "A solar system term.",
        "level5": "A cosmic term."
      }
    },
    {
      "word": "COMET",
      "level": 2,
      "tags": [
        "Space",
        "Science",
        "Sky",
        "Travel"
      ],
      "associations": [],
      "clue": "Tail of ice",
      "clues": {
        "level3": "Tail of ice",
        "level1": "Something in space.",
        "level2": "A night-sky object.",
        "level4": "An astronomy word.",
        "level5": "A celestial object."
      }
    },
    {
      "word": "EARTH",
      "level": 2,
      "tags": [
        "Space",
        "Science",
        "Sky",
        "Travel"
      ],
      "associations": [],
      "clue": "Our home planet",
      "clues": {
        "level3": "Our home planet",
        "level1": "Something in space.",
        "level2": "A night-sky object.",
        "level4": "An astronomy word.",
        "level5": "A celestial object."
      }
    },
    {
      "word": "MARS",
      "level": 2,
      "tags": [
        "Space",
        "Science",
        "Sky",
        "Travel"
      ],
      "associations": [],
      "clue": "Red planet",
      "clues": {
        "level3": "Red planet",
        "level1": "Some starry-sky thing.",
        "level2": "Something seen in the night sky.",
        "level4": "Some solar system term.",
        "level5": "Some cosmic term."
      }
    },
    {
      "word": "NASA",
      "level": 2,
      "tags": [
        "Space",
        "Science",
        "Sky",
        "Travel"
      ],
      "associations": [],
      "clue": "Space agency",
      "clues": {
        "level3": "Space agency",
        "level1": "A starry-sky thing.",
        "level2": "Something seen in the night sky.",
        "level4": "A solar system term.",
        "level5": "A cosmic term."
      }
    },
    {
      "word": "PLANET",
      "level": 2,
      "tags": [
        "Space"
      ],
      "clue": "Orbiting world",
      "associations": [],
      "clues": {
        "level3": "Orbiting world",
        "level1": "Something in space.",
        "level2": "A night-sky object.",
        "level4": "An astronomy word.",
        "level5": "A celestial object."
      }
    },
    {
      "word": "ROCKET",
      "level": 2,
      "tags": [
        "Space",
        "Science",
        "Sky",
        "Travel"
      ],
      "associations": [],
      "clue": "Space launcher",
      "clues": {
        "level3": "Space launcher",
        "level1": "Something in space.",
        "level2": "A night-sky object.",
        "level4": "An astronomy word.",
        "level5": "A celestial object."
      }
    },
    {
      "word": "ASTRONAUT",
      "level": 3,
      "tags": [
        "Space"
      ],
      "clue": "Space explorer",
      "associations": [],
      "clues": {
        "level3": "Space explorer",
        "level1": "A starry-sky thing.",
        "level2": "Something seen in the night sky.",
        "level4": "A solar system term.",
        "level5": "A cosmic term."
      }
    },
    {
      "word": "BLACK HOLE",
      "level": 3,
      "tags": [
        "Space"
      ],
      "clue": "Cosmic void",
      "associations": [],
      "clues": {
        "level3": "Cosmic void",
        "level1": "A starry-sky thing.",
        "level2": "Something seen in the night sky.",
        "level4": "A solar system term.",
        "level5": "A cosmic term."
      }
    },
    {
      "word": "GALAXY",
      "level": 3,
      "tags": [
        "Space",
        "Science",
        "Sky",
        "Travel"
      ],
      "associations": [],
      "clue": "Star collection",
      "clues": {
        "level3": "Star collection",
        "level1": "Something in space.",
        "level2": "A night-sky object.",
        "level4": "An astronomy word.",
        "level5": "A celestial object."
      }
    },
    {
      "word": "GRAVITY",
      "level": 3,
      "tags": [
        "Space",
        "Science",
        "Sky",
        "Travel"
      ],
      "associations": [],
      "clue": "Pulling force",
      "clues": {
        "level3": "Pulling force",
        "level1": "Something in space.",
        "level2": "A night-sky object.",
        "level4": "An astronomy word.",
        "level5": "A celestial object."
      }
    },
    {
      "word": "JUPITER",
      "level": 3,
      "tags": [
        "Space",
        "Science",
        "Sky",
        "Travel"
      ],
      "associations": [],
      "clue": "Giant planet",
      "clues": {
        "level3": "Giant planet",
        "level1": "A starry-sky thing.",
        "level2": "Something seen in the night sky.",
        "level4": "A solar system term.",
        "level5": "A cosmic term."
      }
    },
    {
      "word": "METEOR",
      "level": 3,
      "tags": [
        "Space",
        "Science",
        "Sky",
        "Travel"
      ],
      "associations": [],
      "clue": "Shooting star",
      "clues": {
        "level3": "Shooting star",
        "level1": "Something in space.",
        "level2": "A night-sky object.",
        "level4": "An astronomy word.",
        "level5": "A celestial object."
      }
    },
    {
      "word": "NEBULA",
      "level": 3,
      "tags": [
        "Space",
        "Science",
        "Sky",
        "Travel"
      ],
      "associations": [],
      "clue": "Cosmic cloud",
      "clues": {
        "level3": "Cosmic cloud",
        "level1": "A starry-sky thing.",
        "level2": "Something seen in the night sky.",
        "level4": "A solar system term.",
        "level5": "A cosmic term."
      }
    },
    {
      "word": "ORBIT",
      "level": 3,
      "tags": [
        "Space",
        "Science",
        "Sky",
        "Travel"
      ],
      "associations": [],
      "clue": "Planetary path",
      "clues": {
        "level3": "Planetary path",
        "level1": "Something in space.",
        "level2": "A night-sky object.",
        "level4": "An astronomy word.",
        "level5": "A celestial object."
      }
    },
    {
      "word": "BAT",
      "level": 1,
      "tags": [
        "Sports",
        "Hobbies",
        "Play",
        "Exercise"
      ],
      "associations": [],
      "clue": "Word from Sports",
      "clues": {
        "level1": "A 3-letter sports answer",
        "level2": "Related to sports",
        "level3": "Something linked to sports",
        "level4": "Topic: Sports",
        "level5": "A 3-letter word about sports"
      }
    },
    {
      "word": "FUN",
      "level": 1,
      "tags": [
        "Sports",
        "Hobbies",
        "Play",
        "Exercise"
      ],
      "associations": [],
      "clue": "Word from Sports",
      "clues": {
        "level1": "Topic: Sports",
        "level2": "A 3-letter word about sports",
        "level3": "A 3-letter sports answer",
        "level4": "Related to sports",
        "level5": "Something linked to sports"
      }
    },
    {
      "word": "GYM",
      "level": 1,
      "tags": [
        "Sports",
        "Hobbies",
        "Play",
        "Exercise"
      ],
      "associations": [],
      "clue": "Exercise room",
      "clues": {
        "level3": "Exercise room",
        "level1": "Something linked to sports",
        "level2": "Topic: Sports",
        "level4": "A 3-letter sports answer",
        "level5": "Related to sports"
      }
    },
    {
      "word": "RUN",
      "level": 1,
      "tags": [
        "Sports",
        "Hobbies",
        "Play",
        "Exercise"
      ],
      "associations": [],
      "clue": "Word from Sports",
      "clues": {
        "level1": "A 3-letter sports answer",
        "level2": "Related to sports",
        "level3": "Something linked to sports",
        "level4": "Topic: Sports",
        "level5": "A 3-letter word about sports"
      }
    },
    {
      "word": "WIN",
      "level": 1,
      "tags": [
        "Sports",
        "Hobbies",
        "Play",
        "Exercise"
      ],
      "associations": [],
      "clue": "Word from Sports",
      "clues": {
        "level1": "Topic: Sports",
        "level2": "A 3-letter word about sports",
        "level3": "A 3-letter sports answer",
        "level4": "Related to sports",
        "level5": "Something linked to sports"
      }
    },
    {
      "word": "BALL",
      "level": 2,
      "tags": [
        "Sports",
        "Hobbies",
        "Play",
        "Exercise"
      ],
      "associations": [],
      "clue": "Word from Sports",
      "clues": {
        "level1": "Topic: Sports",
        "level2": "A 4-letter word about sports",
        "level3": "A 4-letter sports answer",
        "level4": "Related to sports",
        "level5": "Something linked to sports"
      }
    },
    {
      "word": "FOOTBALL",
      "level": 2,
      "tags": [
        "Sports"
      ],
      "clue": "Gridiron game",
      "clues": {
        "level3": "Gridiron game",
        "level1": "A 8-letter sports answer",
        "level2": "Related to sports",
        "level4": "Topic: Sports",
        "level5": "A 8-letter word about sports"
      }
    },
    {
      "word": "GOAL",
      "level": 2,
      "tags": [
        "Sports",
        "Hobbies",
        "Play",
        "Exercise"
      ],
      "associations": [],
      "clue": "Word from Sports",
      "clues": {
        "level1": "Related to sports",
        "level2": "Something linked to sports",
        "level3": "Topic: Sports",
        "level4": "A 4-letter word about sports",
        "level5": "A 4-letter sports answer"
      }
    },
    {
      "word": "KICK",
      "level": 2,
      "tags": [
        "Sports",
        "Hobbies",
        "Play",
        "Exercise"
      ],
      "associations": [],
      "clue": "Word from Sports",
      "clues": {
        "level1": "A 4-letter sports answer",
        "level2": "Related to sports",
        "level3": "Something linked to sports",
        "level4": "Topic: Sports",
        "level5": "A 4-letter word about sports"
      }
    },
    {
      "word": "RACE",
      "level": 2,
      "tags": [
        "Sports",
        "Hobbies",
        "Play",
        "Exercise"
      ],
      "associations": [],
      "clue": "Word from Sports",
      "clues": {
        "level1": "Topic: Sports",
        "level2": "A 4-letter word about sports",
        "level3": "A 4-letter sports answer",
        "level4": "Related to sports",
        "level5": "Something linked to sports"
      }
    },
    {
      "word": "SWIM",
      "level": 2,
      "tags": [
        "Sports",
        "Hobbies",
        "Play",
        "Exercise"
      ],
      "associations": [],
      "clue": "Word from Sports",
      "clues": {
        "level1": "A 4-letter sports answer",
        "level2": "Related to sports",
        "level3": "Something linked to sports",
        "level4": "Topic: Sports",
        "level5": "A 4-letter word about sports"
      }
    },
    {
      "word": "TEAM",
      "level": 2,
      "tags": [
        "Sports",
        "Hobbies",
        "Play",
        "Exercise"
      ],
      "associations": [],
      "clue": "Word from Sports",
      "clues": {
        "level1": "A 4-letter sports answer",
        "level2": "Related to sports",
        "level3": "Something linked to sports",
        "level4": "Topic: Sports",
        "level5": "A 4-letter word about sports"
      }
    },
    {
      "word": "VOLLEYBALL",
      "level": 2,
      "tags": [
        "Sports"
      ],
      "clue": "Beach ball game",
      "clues": {
        "level3": "Beach ball game",
        "level1": "Topic: Sports",
        "level2": "A 10-letter word about sports",
        "level4": "Related to sports",
        "level5": "Something linked to sports"
      }
    },
    {
      "word": "BADMINTON",
      "level": 3,
      "tags": [
        "Sports"
      ],
      "clue": "Shuttlecock game",
      "associations": [],
      "clues": {
        "level3": "Shuttlecock game",
        "level1": "Topic: Sports",
        "level2": "A 9-letter word about sports",
        "level4": "Related to sports",
        "level5": "Something linked to sports"
      }
    },
    {
      "word": "BASEBALL",
      "level": 3,
      "tags": [
        "Sports",
        "Hobbies",
        "Play",
        "Exercise"
      ],
      "associations": [],
      "clue": "Diamond sport",
      "clues": {
        "level3": "Diamond sport",
        "level1": "Related to sports",
        "level2": "Something linked to sports",
        "level4": "A 8-letter word about sports",
        "level5": "A 8-letter sports answer"
      }
    },
    {
      "word": "HELMET",
      "level": 3,
      "tags": [
        "Sports",
        "Hobbies",
        "Play",
        "Exercise"
      ],
      "associations": [],
      "clue": "Word from Sports",
      "clues": {
        "level1": "Something linked to sports",
        "level2": "Topic: Sports",
        "level3": "A 6-letter word about sports",
        "level4": "A 6-letter sports answer",
        "level5": "Related to sports"
      }
    },
    {
      "word": "KARATE",
      "level": 3,
      "tags": [
        "Sports"
      ],
      "clue": "Martial art",
      "associations": [],
      "clues": {
        "level3": "Martial art",
        "level1": "A 6-letter sports answer",
        "level2": "Related to sports",
        "level4": "Topic: Sports",
        "level5": "A 6-letter word about sports"
      }
    },
    {
      "word": "SOCCER",
      "level": 3,
      "tags": [
        "Sports",
        "Hobbies",
        "Play",
        "Exercise"
      ],
      "associations": [],
      "clue": "Football game",
      "clues": {
        "level3": "Football game",
        "level1": "Something linked to sports",
        "level2": "Topic: Sports",
        "level4": "A 6-letter sports answer",
        "level5": "Related to sports"
      }
    },
    {
      "word": "STADIUM",
      "level": 3,
      "tags": [
        "Sports",
        "Hobbies",
        "Play",
        "Exercise"
      ],
      "associations": [],
      "clue": "Word from Sports",
      "clues": {
        "level1": "A 7-letter sports answer",
        "level2": "Related to sports",
        "level3": "Something linked to sports",
        "level4": "Topic: Sports",
        "level5": "A 7-letter word about sports"
      }
    },
    {
      "word": "TENNIS",
      "level": 3,
      "tags": [
        "Sports",
        "Hobbies",
        "Play",
        "Exercise"
      ],
      "associations": [],
      "clue": "Racket sport",
      "clues": {
        "level3": "Racket sport",
        "level1": "Some 6-letter sports answer",
        "level2": "Related to sports",
        "level4": "Topic: Sports",
        "level5": "Some 6-letter word about sports"
      }
    },
    {
      "word": "TROPHY",
      "level": 3,
      "tags": [
        "Sports",
        "Hobbies",
        "Play",
        "Exercise"
      ],
      "associations": [],
      "clue": "Word from Sports",
      "clues": {
        "level1": "Related to sports",
        "level2": "Something linked to sports",
        "level3": "Topic: Sports",
        "level4": "A 6-letter word about sports",
        "level5": "A 6-letter sports answer"
      }
    },
    {
      "word": "BICYCLE",
      "level": 2,
      "tags": [
        "Transport"
      ],
      "clue": "Two-pedal ride",
      "associations": [],
      "clues": {
        "level3": "Two-pedal ride",
        "level1": "Something linked to transport",
        "level2": "Topic: Transport",
        "level4": "A 7-letter transport answer",
        "level5": "Related to transport"
      }
    },
    {
      "word": "SHIP",
      "level": 2,
      "tags": [
        "Transport"
      ],
      "clue": "Ocean vessel",
      "associations": [],
      "clues": {
        "level3": "Ocean vessel",
        "level1": "Topic: Transport",
        "level2": "A 4-letter word about transport",
        "level4": "Related to transport",
        "level5": "Something linked to transport"
      }
    },
    {
      "word": "HELICOPTER",
      "level": 3,
      "tags": [
        "Transport"
      ],
      "clue": "Chopper in the sky",
      "clues": {
        "level3": "Chopper in the sky",
        "level1": "Related to transport",
        "level2": "Something linked to transport",
        "level4": "A 10-letter word about transport",
        "level5": "A 10-letter transport answer"
      }
    },
    {
      "word": "MOTORCYCLE",
      "level": 3,
      "tags": [
        "Transport"
      ],
      "clue": "Two-wheeled speed machine",
      "clues": {
        "level3": "Two-wheeled speed machine",
        "level1": "A 10-letter word about transport",
        "level2": "A 10-letter transport answer",
        "level4": "Something linked to transport",
        "level5": "Topic: Transport"
      }
    },
    {
      "word": "CARROT",
      "level": 1,
      "tags": [
        "Vegetables"
      ],
      "clue": "Orange root veggie",
      "clues": {
        "level3": "Orange root veggie",
        "level1": "A 6-letter word about vegetables",
        "level2": "A 6-letter vegetables answer",
        "level4": "Something linked to vegetables",
        "level5": "Topic: Vegetables"
      }
    },
    {
      "word": "POTATO",
      "level": 1,
      "tags": [
        "Vegetables"
      ],
      "clue": "Starchy tuber",
      "clues": {
        "level3": "Starchy tuber",
        "level1": "Related to vegetables",
        "level2": "Something linked to vegetables",
        "level4": "A 6-letter word about vegetables",
        "level5": "A 6-letter vegetables answer"
      }
    },
    {
      "word": "BROCCOLI",
      "level": 2,
      "tags": [
        "Vegetables"
      ],
      "clue": "Green tree veggie",
      "clues": {
        "level3": "Green tree veggie",
        "level1": "A 8-letter word about vegetables",
        "level2": "A 8-letter vegetables answer",
        "level4": "Something linked to vegetables",
        "level5": "Topic: Vegetables"
      }
    },
    {
      "word": "LETTUCE",
      "level": 2,
      "tags": [
        "Vegetables"
      ],
      "clue": "Leafy green",
      "associations": [],
      "clues": {
        "level3": "Leafy green",
        "level1": "A 7-letter word about vegetables",
        "level2": "A 7-letter vegetables answer",
        "level4": "Something linked to vegetables",
        "level5": "Topic: Vegetables"
      }
    },
    {
      "word": "CONE",
      "level": 1,
      "tags": [
        "Vehicles",
        "City",
        "Jobs",
        "Trucks"
      ],
      "associations": [],
      "clue": "Word from Vehicles",
      "clues": {
        "level1": "A ride you can take.",
        "level2": "A way to travel.",
        "level3": "A transport word.",
        "level4": "A transport term.",
        "level5": "A mobility word."
      }
    },
    {
      "word": "DIG",
      "level": 1,
      "tags": [
        "Vehicles",
        "City",
        "Jobs",
        "Trucks",
        "Dinosaurs",
        "History",
        "Animals",
        "Science"
      ],
      "associations": [],
      "clue": "Word from Vehicles",
      "clues": {
        "level1": "Something you can ride in.",
        "level2": "A vehicle you might see.",
        "level3": "A type of vehicle.",
        "level4": "A travel term.",
        "level5": "A transit word."
      }
    },
    {
      "word": "HAT",
      "level": 1,
      "tags": [
        "Vehicles",
        "City",
        "Jobs",
        "Trucks"
      ],
      "associations": [],
      "clue": "Word from Vehicles",
      "clues": {
        "level1": "A ride you can take.",
        "level2": "A way to travel.",
        "level3": "A transport word.",
        "level4": "A transport term.",
        "level5": "A mobility word."
      }
    },
    {
      "word": "ROAD",
      "level": 1,
      "tags": [
        "Vehicles",
        "City",
        "Jobs",
        "Trucks"
      ],
      "associations": [],
      "clue": "Word from Vehicles",
      "clues": {
        "level1": "Something you can ride in.",
        "level2": "A vehicle you might see.",
        "level3": "A type of vehicle.",
        "level4": "A travel term.",
        "level5": "A transit word."
      }
    },
    {
      "word": "TOOL",
      "level": 1,
      "tags": [
        "Vehicles",
        "City",
        "Jobs",
        "Trucks"
      ],
      "associations": [],
      "clue": "Word from Vehicles",
      "clues": {
        "level1": "Something you can ride in.",
        "level2": "A vehicle you might see.",
        "level3": "A type of vehicle.",
        "level4": "A travel term.",
        "level5": "A transit word."
      }
    },
    {
      "word": "BRICK",
      "level": 2,
      "tags": [
        "Vehicles",
        "City",
        "Jobs",
        "Trucks"
      ],
      "associations": [],
      "clue": "Word from Vehicles",
      "clues": {
        "level1": "A ride you can take.",
        "level2": "A way to travel.",
        "level3": "A transport word.",
        "level4": "A transport term.",
        "level5": "A mobility word."
      }
    },
    {
      "word": "BUILD",
      "level": 2,
      "tags": [
        "Vehicles",
        "City",
        "Jobs",
        "Trucks"
      ],
      "associations": [],
      "clue": "Word from Vehicles",
      "clues": {
        "level1": "Something you can ride in.",
        "level2": "A vehicle you might see.",
        "level3": "A type of vehicle.",
        "level4": "A travel term.",
        "level5": "A transit word."
      }
    },
    {
      "word": "CRANE",
      "level": 2,
      "tags": [
        "Vehicles",
        "City",
        "Jobs",
        "Trucks"
      ],
      "associations": [],
      "clue": "Word from Vehicles",
      "clues": {
        "level1": "A ride you can take.",
        "level2": "A way to travel.",
        "level3": "A transport word.",
        "level4": "A transport term.",
        "level5": "A mobility word."
      }
    },
    {
      "word": "DRILL",
      "level": 2,
      "tags": [
        "Vehicles",
        "City",
        "Jobs",
        "Trucks"
      ],
      "associations": [],
      "clue": "Word from Vehicles",
      "clues": {
        "level1": "A ride you can take.",
        "level2": "A way to travel.",
        "level3": "A transport word.",
        "level4": "A transport term.",
        "level5": "A mobility word."
      }
    },
    {
      "word": "TRUCK",
      "level": 2,
      "tags": [
        "Vehicles",
        "City",
        "Jobs",
        "Trucks"
      ],
      "associations": [],
      "clue": "Hauling vehicle",
      "clues": {
        "level3": "Hauling vehicle",
        "level1": "A ride you can take.",
        "level2": "A way to travel.",
        "level4": "A transport term.",
        "level5": "A mobility word."
      }
    },
    {
      "word": "WORK",
      "level": 2,
      "tags": [
        "Vehicles",
        "City",
        "Jobs",
        "Trucks"
      ],
      "associations": [],
      "clue": "Word from Vehicles",
      "clues": {
        "level1": "A ride you can take.",
        "level2": "A way to travel.",
        "level3": "A transport word.",
        "level4": "A transport term.",
        "level5": "A mobility word."
      }
    },
    {
      "word": "ASPHALT",
      "level": 3,
      "tags": [
        "Vehicles",
        "City",
        "Jobs",
        "Trucks"
      ],
      "associations": [],
      "clue": "Word from Vehicles",
      "clues": {
        "level1": "A ride you can take.",
        "level2": "A way to travel.",
        "level3": "A transport word.",
        "level4": "A transport term.",
        "level5": "A mobility word."
      }
    },
    {
      "word": "BULLDOZER",
      "level": 3,
      "tags": [
        "Vehicles",
        "City",
        "Jobs",
        "Trucks"
      ],
      "associations": [],
      "clue": "Word from Vehicles",
      "clues": {
        "level1": "A ride you can take.",
        "level2": "A way to travel.",
        "level3": "A transport word.",
        "level4": "A transport term.",
        "level5": "A mobility word."
      }
    },
    {
      "word": "CEMENT",
      "level": 3,
      "tags": [
        "Vehicles",
        "City",
        "Jobs",
        "Trucks"
      ],
      "associations": [],
      "clue": "Word from Vehicles",
      "clues": {
        "level1": "Something you can ride in.",
        "level2": "A vehicle you might see.",
        "level3": "A type of vehicle.",
        "level4": "A travel term.",
        "level5": "A transit word."
      }
    },
    {
      "word": "HAMMER",
      "level": 3,
      "tags": [
        "Vehicles",
        "City",
        "Jobs",
        "Trucks"
      ],
      "associations": [],
      "clue": "Word from Vehicles",
      "clues": {
        "level1": "Something you can ride in.",
        "level2": "A vehicle you might see.",
        "level3": "A type of vehicle.",
        "level4": "A travel term.",
        "level5": "A transit word."
      }
    },
    {
      "word": "SAFETY",
      "level": 3,
      "tags": [
        "Vehicles",
        "City",
        "Jobs",
        "Trucks"
      ],
      "associations": [],
      "clue": "Word from Vehicles",
      "clues": {
        "level1": "Something you can ride in.",
        "level2": "A vehicle you might see.",
        "level3": "A type of vehicle.",
        "level4": "A travel term.",
        "level5": "A transit word."
      }
    },
    {
      "word": "WRENCH",
      "level": 3,
      "tags": [
        "Vehicles",
        "City",
        "Jobs",
        "Trucks"
      ],
      "associations": [],
      "clue": "Word from Vehicles",
      "clues": {
        "level1": "A ride you can take.",
        "level2": "A way to travel.",
        "level3": "A transport word.",
        "level4": "A transport term.",
        "level5": "A mobility word."
      }
    },
    {
      "word": "COLD",
      "level": 1,
      "tags": [
        "Weather",
        "Nature",
        "Science",
        "Sky"
      ],
      "associations": [],
      "clue": "Word from Weather",
      "clues": {
        "level1": "A kind of weather.",
        "level2": "Sky condition.",
        "level3": "A weather condition.",
        "level4": "A weather description.",
        "level5": "A meteorology term."
      }
    },
    {
      "word": "HOT",
      "level": 1,
      "tags": [
        "Weather",
        "Nature",
        "Science",
        "Sky"
      ],
      "associations": [],
      "clue": "Word from Weather",
      "clues": {
        "level1": "The sky looks this way.",
        "level2": "Weather you can see outside.",
        "level3": "A sky condition word.",
        "level4": "A forecast detail.",
        "level5": "A sky term."
      }
    },
    {
      "word": "RAIN",
      "level": 1,
      "tags": [
        "Weather",
        "Nature",
        "Science",
        "Sky"
      ],
      "associations": [],
      "clue": "Word from Weather",
      "clues": {
        "level1": "A kind of weather.",
        "level2": "Sky condition.",
        "level3": "A weather condition.",
        "level4": "A weather description.",
        "level5": "A meteorology term."
      }
    },
    {
      "word": "SNOW",
      "level": 1,
      "tags": [
        "Weather",
        "Nature",
        "Science",
        "Sky"
      ],
      "associations": [],
      "clue": "Word from Weather",
      "clues": {
        "level1": "The sky looks this way.",
        "level2": "Weather you can see outside.",
        "level3": "A sky condition word.",
        "level4": "A forecast detail.",
        "level5": "A sky term."
      }
    },
    {
      "word": "CLOUD",
      "level": 2,
      "tags": [
        "Weather",
        "Nature",
        "Science",
        "Sky"
      ],
      "associations": [],
      "clue": "Word from Weather",
      "clues": {
        "level1": "The sky looks this way.",
        "level2": "Weather you can see outside.",
        "level3": "A sky condition word.",
        "level4": "A forecast detail.",
        "level5": "A sky term."
      }
    },
    {
      "word": "FALL",
      "level": 2,
      "tags": [
        "Weather",
        "Nature",
        "Science",
        "Sky"
      ],
      "associations": [],
      "clue": "Word from Weather",
      "clues": {
        "level1": "The sky looks this way.",
        "level2": "Weather you can see outside.",
        "level3": "A sky condition word.",
        "level4": "A forecast detail.",
        "level5": "A sky term."
      }
    },
    {
      "word": "HEAT",
      "level": 2,
      "tags": [
        "Weather",
        "Nature",
        "Science",
        "Sky"
      ],
      "associations": [],
      "clue": "Word from Weather",
      "clues": {
        "level1": "A kind of weather.",
        "level2": "Sky condition.",
        "level3": "A weather condition.",
        "level4": "A weather description.",
        "level5": "A meteorology term."
      }
    },
    {
      "word": "SPRING",
      "level": 2,
      "tags": [
        "Weather",
        "Nature",
        "Science",
        "Sky"
      ],
      "associations": [],
      "clue": "Word from Weather",
      "clues": {
        "level1": "The sky looks this way.",
        "level2": "Weather you can see outside.",
        "level3": "A sky condition word.",
        "level4": "A forecast detail.",
        "level5": "A sky term."
      }
    },
    {
      "word": "STORM",
      "level": 2,
      "tags": [
        "Weather",
        "Nature",
        "Science",
        "Sky"
      ],
      "associations": [],
      "clue": "Word from Weather",
      "clues": {
        "level1": "The sky looks this way.",
        "level2": "Weather you can see outside.",
        "level3": "A sky condition word.",
        "level4": "A forecast detail.",
        "level5": "A sky term."
      }
    },
    {
      "word": "WIND",
      "level": 2,
      "tags": [
        "Weather",
        "Nature",
        "Science",
        "Sky"
      ],
      "associations": [],
      "clue": "Word from Weather",
      "clues": {
        "level1": "A kind of weather.",
        "level2": "Sky condition.",
        "level3": "A weather condition.",
        "level4": "A weather description.",
        "level5": "A meteorology term."
      }
    },
    {
      "word": "CLIMATE",
      "level": 3,
      "tags": [
        "Weather",
        "Nature",
        "Science",
        "Sky"
      ],
      "associations": [],
      "clue": "Word from Weather",
      "clues": {
        "level1": "The sky looks this way.",
        "level2": "Weather you can see outside.",
        "level3": "A sky condition word.",
        "level4": "A forecast detail.",
        "level5": "A sky term."
      }
    },
    {
      "word": "LIGHTNING",
      "level": 3,
      "tags": [
        "Weather",
        "Nature",
        "Science",
        "Sky"
      ],
      "associations": [],
      "clue": "Word from Weather",
      "clues": {
        "level1": "A kind of weather.",
        "level2": "Sky condition.",
        "level3": "A weather condition.",
        "level4": "A weather description.",
        "level5": "A meteorology term."
      }
    },
    {
      "word": "SUMMER",
      "level": 3,
      "tags": [
        "Weather",
        "Nature",
        "Science",
        "Sky"
      ],
      "associations": [],
      "clue": "Word from Weather",
      "clues": {
        "level1": "The sky looks this way.",
        "level2": "Weather you can see outside.",
        "level3": "A sky condition word.",
        "level4": "A forecast detail.",
        "level5": "A sky term."
      }
    },
    {
      "word": "THUNDER",
      "level": 3,
      "tags": [
        "Weather",
        "Nature",
        "Science",
        "Sky"
      ],
      "associations": [],
      "clue": "Word from Weather",
      "clues": {
        "level1": "A kind of weather.",
        "level2": "Sky condition.",
        "level3": "A weather condition.",
        "level4": "A weather description.",
        "level5": "A meteorology term."
      }
    },
    {
      "word": "TORNADO",
      "level": 3,
      "tags": [
        "Weather",
        "Nature",
        "Science",
        "Sky"
      ],
      "associations": [],
      "clue": "Word from Weather",
      "clues": {
        "level1": "The sky looks this way.",
        "level2": "Weather you can see outside.",
        "level3": "A sky condition word.",
        "level4": "A forecast detail.",
        "level5": "A sky term."
      }
    },
    {
      "word": "WINTER",
      "level": 3,
      "tags": [
        "Weather",
        "Nature",
        "Science",
        "Sky"
      ],
      "associations": [],
      "clue": "Word from Weather",
      "clues": {
        "level1": "The sky looks this way.",
        "level2": "Weather you can see outside.",
        "level3": "A sky condition word.",
        "level4": "A forecast detail.",
        "level5": "A sky term."
      }
    }
  ]
}